zeroundub/__init__.py
zeroundub/cli/__init__.py
zeroundub/cli/error.py
zeroundub/cli/progress.py
zeroundub/cli/utils.py
zeroundub/cli/cmdline/__init__.py
zeroundub/cli/cmdline/undub.py
zeroundub/gui/__init__.py
zeroundub/gui/tkgui.py
zeroundub/utils/__init__.py
zeroundub/utils/file.py
zeroundub/wagrenier/__init__.py
zeroundub/wagrenier/pssmux.py
zeroundub/zero/__init__.py
zeroundub/zero/dvd.py
zeroundub/zero/pk2.py
zeroundub/zero/tim2.py
zeroundub/zero/iso/__init__.py
zeroundub/zero/iso/repack.py
zeroundub/zero/reader/__init__.py
zeroundub/zero/reader/entry.py
zeroundub/zero/reader/pjzreader.py
zeroundub/zero/reader/adapter/__init__.py
zeroundub/zero/reader/adapter/abstract.py
zeroundub/zero/reader/adapter/filesystem.py
zeroundub/zero/reader/adapter/iso.py
zeroundub/zero/text/__init__.py
zeroundub/zero/text/parser.py
zeroundub/zero/text/tables/__init__.py
zeroundub/zero/text/tables/european.py
zeroundub/zero/text/tables/japanese.py
zeroundub/zero/text/tables/subtitles.py
zeroundub/zero/text/tables/utils.py
zeroundub-1.3.3.dist-info/LICENSE
zeroundub-1.3.3.dist-info/METADATA
zeroundub-1.3.3.dist-info/WHEEL
zeroundub-1.3.3.dist-info/entry_points.txt
zeroundub-1.3.3.dist-info/top_level.txt
zeroundub-1.3.3.dist-info/RECORD
