Metadata-Version: 2.1
Name: zeroundub
Version: 1.3.3
Summary: Undub project for Tecmo's Project Zero - the EU version (the first one) for the PS2
Author: karas84
Project-URL: Homepage, https://github.com/karas84/ProjectZeroUndub
Classifier: Programming Language :: Python :: 3
Classifier: License :: OSI Approved :: MIT License
Classifier: Operating System :: OS Independent
Requires-Python: >=3.7
License-File: LICENSE
Requires-Dist: numpy (>=1.24.3)
Requires-Dist: pycdlib (>=1.12.0)
Requires-Dist: scipy (>=1.10.1)
Requires-Dist: tqdm (>=4.63.1)
